Mukund/__init__.py
Mukund/main.py
Mukund/core/database.py
Mukund/errors/exceptions.py
Mukund-1.0.3.dist-info/METADATA
Mukund-1.0.3.dist-info/WHEEL
Mukund-1.0.3.dist-info/top_level.txt
Mukund-1.0.3.dist-info/RECORD
