Metadata-Version: 2.1
Name: Mukund
Version: 1.0.3
Summary: An advance package to store data in JSON files and allow to store media with mapping and much more i recommend to atleast use it once
Maintainer: Mukund
Keywords: Database,MukundDrive,MukundDB,Mukund,NoSQL,MukuDB,Mukund-Database
Classifier: Programming Language :: Python :: 3
Classifier: Programming Language :: Python :: 3.7
Classifier: Programming Language :: Python :: 3.8
Classifier: Programming Language :: Python :: 3.9
Classifier: Programming Language :: Python :: 3.10
Classifier: Programming Language :: Python :: 3.11
Classifier: Development Status :: 5 - Production/Stable
Classifier: License :: OSI Approved :: MIT License
Classifier: Operating System :: OS Independent
Classifier: Intended Audience :: Developers
Classifier: Natural Language :: English
Requires-Python: ~=3.7
